<?xml version="1.0" encoding="UTF-8"?>
<mei xmlns="http://www.music-encoding.org/ns/mei" meiversion="4.0.1"
     xml:id="mei_idm140693919771456">
   <meiHead xml:id="idm2">
      <fileDesc xml:id="idm3">
         <titleStmt xml:id="idm4">
            <title xml:id="idm5" xml:lang="da">Byd mig at leve</title>
         </titleStmt>
         <pubStmt xml:id="idm6">
            <respStmt xml:id="respStmt_168N2000F">
               <resp xml:id="idm8">Publisher</resp>
               <corpName xml:id="corpName_168N20013">
                  <abbr xml:id="idm10">DCM</abbr>
                  <expan xml:id="idm11">Danish Centre for Music Editing</expan>
                  <address xml:id="idm12">
                     <addrLine xml:id="idm13">Royal Danish Library</addrLine>
                     <addrLine xml:id="idm14">Søren Kierkegaards Plads 1</addrLine>
                     <addrLine xml:id="idm15">P.O. Box 2149</addrLine>
                     <addrLine xml:id="idm16">DK - 1016 Copenhagen K</addrLine>
                     <addrLine xml:id="idm17">
                        <ptr label="WWW" target="https://www.kb.dk" xml:id="ptr_N2026F"/>
                     </addrLine>
                     <addrLine xml:id="idm19">
                        <ptr label="E-mail" xml:id="ptr_N20273" target="mailto://kb@kb.dk"/>
                     </addrLine>
                  </address>
               </corpName>
               <persName role="editor" xml:id="persName_168N2002B">Niels Bo Foltmann</persName>
               <persName role="editor" xml:id="persName_168N2002F">Axel Teich Geertinger</persName>
               <persName role="editor" xml:id="persName_168N20033">Peter Hauge</persName>
               <persName role="editor" xml:id="persName_168N20037">Niels Krabbe</persName>
               <persName role="editor" xml:id="persName_224idm139982703307488">Bjarke Moe</persName>
               <persName role="programmer" xml:id="persName_b2b72a5e">Sigfrid Lundberg</persName>
               <persName role="secretary" xml:id="persName_ad16385b">Katarina Smitt Engberg</persName>
               <persName role="secretary" xml:id="persName_4352b12d">Niclas Nørby Hundahl</persName>
               <persName role="editor" xml:id="persName_228idm140379300124272">Bjarke Moe</persName>
               <persName role="editor" xml:id="persName_168N2003B">Elly Bruunshuus Petersen</persName>
               <persName role="programmer" xml:id="persName_553deab9">Sigfrid Lundberg</persName>
               <persName role="secretary" xml:id="persName_d11c1ae0">Katarina Smitt Engberg</persName>
               <persName role="secretary" xml:id="persName_abbec998">Niclas Nørby Hundahl</persName>
            </respStmt>
            <date xml:id="idm34" isodate="2014">2014</date>
         </pubStmt>
         <seriesStmt xml:id="idm35">
            <title xml:id="title_168N20049">Carl Nielsen Works</title>
            <identifier type="file_collection" xml:id="identifier_168N2004D">CNW</identifier>
         </seriesStmt>
      </fileDesc>
      <encodingDesc xml:id="idm85">
         <appInfo xml:id="idm86">
            <application xml:id="idm87" version="2013">
               <name xml:id="idm88">MerMEId</name>
               <ptr label="MerMEId project home page"
                    target="http://www.kb.dk/en/nb/dcm/projekter/mermeid.html"
                    xml:id="ptr_N2034F"/>
            </application>
         </appInfo>
         <projectDesc xml:id="projectDesc_168N20097">
            <p xml:id="idm91">Metadata created using MerMEId 2013.</p>
         </projectDesc>
         <classDecls>
            <taxonomy xml:id="DcmSourceClassification">
               <category xml:id="DcmContentClass"/>
               <category xml:id="DcmPresentationClass"/>
               <category xml:id="DcmAuthorityClass"/>
               <category xml:id="DcmScoringClass"/>
               <category xml:id="DcmStateClass"/>
               <category xml:id="DcmCompletenessClass"/>
            </taxonomy>
         </classDecls>
      </encodingDesc>
      <workList xml:id="idm92">
         <work xml:id="work_d1e191187">
            <identifier xml:id="idm94" label="CNW">355</identifier>
            <identifier xml:id="idm95" label="CNU">III/6, 315</identifier>
            <identifier xml:id="idm96" label="CNS">287</identifier>
            <identifier xml:id="idm97" label="FS">3t</identifier>
            <title xml:id="title_3111150c" xml:lang="da">Byd mig at leve</title>
            <title xml:id="title_c1e3e065" xml:lang="en">Bid me to live</title>
            <contributor xml:id="idm101">
               <persName role="composer" xml:id="persName_168N200B2">Carl Nielsen</persName>
               <persName role="author" xml:id="persName_168N200B6">Robert Herrick</persName>
               <persName role="translator" xml:id="persName_d9e9f0cd">Caralis [Christian Preetzmann]</persName>
            </contributor>
            <creation xml:id="creation_168N200BB">
               <date xml:id="idm106" notafter="1888" notbefore="1886">Between c. 1886 and 1888</date>
            </creation>
            <history xml:id="history_168N200B9">
               <p xml:id="idm108">Like a number of other works (CNW <ref xmlns:xl="http://www.w3.org/1999/xlink" xml:id="idm109"
                       target="document.xq?doc=cnw0276.xml"
                       xl:show="replace"
                       label="CNW 276">276</ref>, <ref xmlns:xl="http://www.w3.org/1999/xlink" xml:id="idm110"
                       target="document.xq?doc=cnw0277.xml"
                       xl:show="replace"
                       label="CNW 277">277</ref>, <ref xmlns:xl="http://www.w3.org/1999/xlink" xml:id="idm111"
                       target="document.xq?doc=cnw0278.xml"
                       xl:show="replace"
                       label="CNW 278">278</ref>, <ref xmlns:xl="http://www.w3.org/1999/xlink" xml:id="idm112"
                       target="document.xq?doc=cnw0279.xml"
                       xl:show="replace"
                       label="CNW 279">279</ref>, <ref xmlns:xl="http://www.w3.org/1999/xlink" xml:id="idm113"
                       target="document.xq?doc=cnw0358.xml"
                       xl:show="replace"
                       label="CNW 356">356</ref>, <ref xmlns:xl="http://www.w3.org/1999/xlink" xml:id="idm114"
                       target="document.xq?doc=cnw0359.xml"
                       xl:show="replace"
                       label="CNW 357">357</ref>, <ref xmlns:xl="http://www.w3.org/1999/xlink" xml:id="idm115"
                       target="document.xq?doc=cnw0360.xml"
                       xl:show="replace"
                       label="CNW 358">358</ref>), the present composition for male choir dates from Nielsen's student years and may have been written at the suggestion of his theory teacher, Orla Rosenhoff.</p>
            </history>
            <langUsage xml:id="idm116">
               <language xml:id="da">Danish</language>
               <language xml:id="en">English</language>
            </langUsage>
            <notesStmt xml:id="idm119">
               <annot label="" type="links" xml:id="annot_168N200D7">
                  <ptr label="Carl Nielsen Edition (Editorial Texts)" mimetype=""
                       target="/dcm/assets/cnu/pdf/CNU_III_07_songs_4.pdf"
                       xml:id="ptr_a0b4c03f"/>
               </annot>
            </notesStmt>
            <classification xml:id="idm122">
               <termList xml:id="idm129">
                  <term xml:id="idm130">Vocal music</term>
                  <term xml:id="idm131">A cappella choral music</term>
               </termList>
            </classification>
            <expressionList xml:id="idm132">
               <expression xml:id="expression_1">
                  <title xml:id="title_168N200F8" xml:lang="da"/>
                  <incip xml:id="incip_168N200FF">
                     <incipText xml:id="incipText_168N20101">
                        <p xml:id="idm138" xml:lang="da">Byd mig at leve</p>
                        <p xml:id="idm139" xml:lang="en">Bid me to live</p>
                     </incipText>
                     <graphic target="/dcm/assets/udgivelser/cnw/incipits/lowres/cnw_355.png" label=""
                              targettype="lowres"
                              xml:id="graphic_168N2010C"/>
                     <graphic target="/dcm/assets/udgivelser/cnw/incipits/hires/cnw_355.png" label=""
                              targettype="hires"
                              xml:id="graphic_168N20111"/>
                  </incip>
                  <tempo xml:id="idm143">Andantino</tempo>
                  <meter xml:id="idm144" count="6" unit="8"/>
                  <history xml:id="history_168N20124">
                     <eventList type="performances" xml:id="eventList_168N20132">
                        <event xml:id="event_d1e338331"/>
                     </eventList>
                     <p xml:id="idm148"/>
                  </history>
                  <perfMedium analog="marc:048" xml:id="perfMedium_168N20146">
                     <perfResList xml:id="idm150">
                        <perfResList codedval="cc" xml:id="perfResList_168N2014B">
                           <head xml:id="idm152">Choir</head>
                           <perfRes codedval="vd" count="1" xml:id="perfRes_6176c9cc">T.</perfRes>
                           <perfRes codedval="vd" count="1" xml:id="perfRes_81a23aba">T.</perfRes>
                           <perfRes codedval="vf" count="1" xml:id="perfRes_8d46787a">B.</perfRes>
                           <perfRes codedval="vf" count="1" xml:id="perfRes_588b83bd">B.</perfRes>
                        </perfResList>
                     </perfResList>
                  </perfMedium>
                  <relationList xml:id="idm157">
                     <relation label="Carl Nielsen Edition" rel="hasReproduction"
                               target="http://www.kb.dk/export/sites/kb_dk/da/nb/dcm/cnu/pdf/CNU_III_06_songs_3.pdf#page=78"
                               targettype="edited_score"
                               xml:id="relation_168N2015F"/>
                  </relationList>
               </expression>
            </expressionList>
         </work>
      </workList>
      <manifestationList xml:id="idm38">
         <manifestation label="" xml:id="source_d1e37">
            <titleStmt xml:id="idm40">
               <title xml:id="title_168N2005B">Score, autograph, fair copy</title>
            </titleStmt>
            <pubStmt xml:id="idm43"/>
            <classification xml:id="idm45">
               <termList xml:id="idm46">
                  <term xml:id="idm47" class="#DcmContentClass">notated music</term>
                  <term xml:id="idm48" class="#DcmPresentationClass">manuscript</term>
                  <term xml:id="idm49" class="#DcmAuthorityClass">autograph</term>
                  <term xml:id="idm50" class="#DcmScoringClass">score</term>
                  <term xml:id="idm51" class="#DcmStateClass">fair copy</term>
                  <term xml:id="idm52" class="#DcmCompletenessClass">complete</term>
               </termList>
            </classification>
            <itemList xml:id="idm53">
               <item label="" xml:id="item_1ef96499">
                  <identifier xml:id="idm55" label="CNU Source">A</identifier>
                  <physLoc xml:id="idm56">
                     <repository xml:id="idm57">
                        <identifier auth.uri="http://www.rism.info" auth="RISM" xml:id="identifier_ba16b6ae">DK-Kk</identifier>
                        <ptr label="Facsimile" mimetype="" target="/dcm/ma/CarlNielsen/cns287.pdf"
                             xml:id="ptr_26edab3a"/>
                     </repository>
                     <identifier xml:id="identifier_b71987de">CNS 287</identifier>
                  </physLoc>
               </item>
            </itemList>
            <relationList xml:id="idm61">
               <relation label="" rel="isEmbodimentOf" target="#expression_1"
                         xml:id="relation_168N2008C"/>
            </relationList>
         </manifestation>
         <manifestation label="" xml:id="source_70f97e69">
            <identifier xml:id="idm64" label="CNU Source">B</identifier>
            <titleStmt xml:id="idm65">
               <title xml:id="title_ec471a41">Text, print</title>
            </titleStmt>
            <pubStmt xml:id="idm67">
               <pubPlace xml:id="pubPlace_d267f4a6">Copenhagen</pubPlace>
               <date xml:id="idm69" isodate="1867">1867</date>
            </pubStmt>
            <notesStmt xml:id="idm70">
               <annot type="source_description" xml:id="annot_d54e15c2">
                  <p xml:id="idm72">Printed in: Caralis [Christian Preetzmann], <rend xml:id="idm73" fontstyle="italic">Digte og Sange</rend>, pp. 25–26.</p>
               </annot>
            </notesStmt>
            <classification xml:id="idm74">
               <termList xml:id="idm75">
                  <term xml:id="idm76" class="#DcmContentClass">text</term>
                  <term xml:id="idm77" class="#DcmPresentationClass">print</term>
                  <term xml:id="idm78" class="#DcmAuthorityClass"/>
                  <term xml:id="idm79" class="#DcmScoringClass"/>
                  <term xml:id="idm80" class="#DcmStateClass"/>
                  <term xml:id="idm81" class="#DcmCompletenessClass">complete</term>
               </termList>
            </classification>
            <itemList xml:id="idm82"/>
            <relationList xml:id="idm83">
               <relation label="" rel="isEmbodimentOf" target="#expression_1" xml:id="relation_625aca5a"/>
            </relationList>
         </manifestation>
      </manifestationList>
      <revisionDesc xml:id="idm159">
         <change isodate="2012-01-24" xml:id="change_d1e397390">
            <respStmt xml:id="idm161">
               <name xml:id="idm162">ebp</name>
            </respStmt>
            <changeDesc xml:id="idm163">
               <p xml:id="idm164">tab.1</p>
            </changeDesc>
         </change>
         <change isodate="2013-09-03" xml:id="change_162d1e181">
            <respStmt xml:id="idm166">
               <name xml:id="idm167">MerMEId</name>
            </respStmt>
            <changeDesc xml:id="idm168">
               <p xml:id="idm169">Automated conversion from MEI 2012 to MEI 2013</p>
            </changeDesc>
         </change>
         <change isodate="2014-02-19" xml:id="change_168N20186">
            <respStmt xml:id="idm171">
               <name xml:id="idm172">ph</name>
            </respStmt>
            <changeDesc xml:id="idm173">
               <p xml:id="idm174"/>
            </changeDesc>
         </change>
         <change isodate="2014-03-20" xml:id="change_69ece5e7">
            <respStmt xml:id="idm176">
               <name xml:id="idm177">ph</name>
            </respStmt>
            <changeDesc xml:id="idm178">
               <p xml:id="idm179"/>
            </changeDesc>
         </change>
         <change isodate="2014-03-26" xml:id="change_224N2020F">
            <respStmt xml:id="idm181">
               <name xml:id="idm182">ph</name>
            </respStmt>
            <changeDesc xml:id="idm183">
               <p xml:id="idm184"/>
            </changeDesc>
         </change>
         <change isodate="2014-04-15" xml:id="change_65a383ea">
            <respStmt xml:id="idm186">
               <name xml:id="idm187">kaen</name>
            </respStmt>
            <changeDesc xml:id="idm188">
               <p xml:id="idm189"/>
            </changeDesc>
         </change>
         <change isodate="2014-05-26" xml:id="change_235N2023A">
            <respStmt xml:id="idm191">
               <name xml:id="idm192">kaen</name>
            </respStmt>
            <changeDesc xml:id="idm193">
               <p xml:id="idm194"/>
            </changeDesc>
         </change>
         <change isodate="2014-05-30" xml:id="change_1492a730">
            <respStmt xml:id="idm196">
               <name xml:id="idm197">kaen</name>
            </respStmt>
            <changeDesc xml:id="idm198">
               <p xml:id="idm199"/>
            </changeDesc>
         </change>
         <change isodate="2014-06-13" xml:id="change_231N20230">
            <respStmt xml:id="idm201">
               <name xml:id="idm202">bmoe</name>
            </respStmt>
            <changeDesc xml:id="idm203">
               <p xml:id="idm204"/>
            </changeDesc>
         </change>
         <change isodate="2014-09-16" xml:id="change_f2192651">
            <respStmt xml:id="idm206">
               <name xml:id="idm207">kaen</name>
            </respStmt>
            <changeDesc xml:id="idm208">
               <p xml:id="idm209"/>
            </changeDesc>
         </change>
         <change isodate="2014-09-24" xml:id="change_240N2024E">
            <respStmt xml:id="idm211">
               <name xml:id="idm212">ph</name>
            </respStmt>
            <changeDesc xml:id="idm213">
               <p xml:id="idm214"/>
            </changeDesc>
         </change>
         <change isodate="2014-09-26" xml:id="change_804fb727">
            <respStmt xml:id="idm216">
               <name xml:id="idm217">atge</name>
            </respStmt>
            <changeDesc xml:id="idm218">
               <p xml:id="idm219"/>
            </changeDesc>
         </change>
         <change isodate="2014-09-30" xml:id="change_238N2024D">
            <respStmt xml:id="idm221">
               <name xml:id="idm222">atge</name>
            </respStmt>
            <changeDesc xml:id="idm223">
               <p xml:id="idm224"/>
            </changeDesc>
         </change>
         <change isodate="2014-10-07" xml:id="change_241N20253">
            <respStmt xml:id="idm226">
               <name xml:id="idm227">kaen</name>
            </respStmt>
            <changeDesc xml:id="idm228">
               <p xml:id="idm229"/>
            </changeDesc>
         </change>
         <change isodate="2014-11-11" xml:id="change_244N20259">
            <respStmt xml:id="idm231">
               <name xml:id="idm232">kaen</name>
            </respStmt>
            <changeDesc xml:id="idm233">
               <p xml:id="idm234"/>
            </changeDesc>
         </change>
         <change isodate="2014-11-20" xml:id="change_244d1e256">
            <respStmt xml:id="idm236">
               <name xml:id="idm237">MerMEId</name>
            </respStmt>
            <changeDesc xml:id="idm238">
               <p xml:id="idm239">Batch transformation moving identifier/@type data to @label</p>
            </changeDesc>
         </change>
         <change isodate="2014-11-20" xml:id="change_247d1e256">
            <respStmt xml:id="idm241">
               <name xml:id="idm242">MerMEId</name>
            </respStmt>
            <changeDesc xml:id="idm243">
               <p xml:id="idm244">Batch transformation ensuring correct order of elements in source, work and biblList</p>
            </changeDesc>
         </change>
         <change isodate="2014-11-20" xml:id="change_250d1e256">
            <respStmt xml:id="idm246">
               <name xml:id="idm247">MerMEId</name>
            </respStmt>
            <changeDesc xml:id="idm248">
               <p xml:id="idm249">Batch transformation removing duplicate IDs and fixing other issues</p>
            </changeDesc>
         </change>
         <change isodate="2014-12-12" xml:id="change_240d1e255">
            <respStmt xml:id="idm251">
               <name xml:id="idm252">atge</name>
            </respStmt>
            <changeDesc xml:id="idm253">
               <p xml:id="idm254">removed indication of key</p>
            </changeDesc>
         </change>
         <change isodate="2015-02-25" xml:id="change_245N20263">
            <respStmt xml:id="idm256">
               <name xml:id="idm257">kaen</name>
            </respStmt>
            <changeDesc xml:id="idm258">
               <p xml:id="idm259"/>
            </changeDesc>
         </change>
         <change isodate="2015-08-11" xml:id="change_248N20269">
            <respStmt xml:id="idm261">
               <name xml:id="idm262">atge</name>
            </respStmt>
            <changeDesc xml:id="idm263">
               <p xml:id="idm264"/>
            </changeDesc>
         </change>
         <change isodate="2016-03-08" xml:id="change_248idm140099936707856">
            <respStmt xml:id="idm266">
               <name xml:id="idm267">MerMEId</name>
            </respStmt>
            <changeDesc xml:id="idm268">
               <p xml:id="idm269">Batch transformation migrating metadata to MerMEId rev. 948+</p>
            </changeDesc>
         </change>
         <change xml:id="idm270" isodate="2016-03-23">
            <respStmt xml:id="idm271">
               <name xml:id="idm272"/>
            </respStmt>
            <changeDesc xml:id="idm273">
               <p xml:id="idm274"/>
            </changeDesc>
         </change>
         <change isodate="2016-03-30" xml:id="change_256d1e256">
            <respStmt xml:id="idm276">
               <name xml:id="idm277">MerMEId</name>
            </respStmt>
            <changeDesc xml:id="idm278">
               <p xml:id="idm279">Batch transformation putting misplaced text back in place</p>
            </changeDesc>
         </change>
         <change isodate="2016-05-24" xml:id="change_259N10286">
            <respStmt xml:id="idm281">
               <name xml:id="idm282">kaen</name>
            </respStmt>
            <changeDesc xml:id="idm283">
               <p xml:id="idm284"/>
            </changeDesc>
         </change>
         <change xml:id="idm285" isodate="2017-04-04" n="26">
            <respStmt xml:id="idm286">
               <name xml:id="idm287">MerMEId</name>
            </respStmt>
            <changeDesc xml:id="idm288">
               <p xml:id="idm289">Converted to version 3.0.0 using mei21To30.xsl, version 1.0 beta for MerMEId</p>
            </changeDesc>
         </change>
         <change isodate="2017-12-05T18:02:47+01:00" xml:id="change_323N101F2">
            <respStmt xml:id="idm291">
               <name xml:id="idm292">MerMEId</name>
            </respStmt>
            <changeDesc xml:id="idm293">
               <p xml:id="idm294">Mail address updated</p>
            </changeDesc>
         </change>
         <change isodate="2017-12-14T16:32:48+01:00" xml:id="change_328N101F2">
            <respStmt xml:id="idm296">
               <name xml:id="idm297">MerMEId</name>
            </respStmt>
            <changeDesc xml:id="idm298">
               <p xml:id="idm299">Batch transformation removing empty elements</p>
            </changeDesc>
         </change>
         <change isodate="2019-11-20T14:55:34Z" xml:id="change_300N101BD">
            <respStmt xml:id="idm301">
               <name xml:id="idm302">MerMEId</name>
            </respStmt>
            <changeDesc xml:id="idm303">
               <p xml:id="idm304">Incipit links updated</p>
            </changeDesc>
         </change>
         <change isodate="2021-06-09" xml:id="change_305d1e244">
            <respStmt>
               <name>MerMEId</name>
            </respStmt>
            <changeDesc>
               <p>Transform from MEI 3.0.0 to 4.0.0</p>
            </changeDesc>
         </change>
         <change isodate="2022-12-02" xml:id="change_308d1e243">
            <respStmt>
               <name>MerMEId</name>
            </respStmt>
            <changeDesc>
               <p>Adjustments for MEI 4.0.1 validation</p>
            </changeDesc>
         </change>
      </revisionDesc>
   </meiHead>
   <music xml:id="idm305"/>
</mei>